<annotation>
	<folder>gen_data</folder>
	<filename>3-146.jpg</filename>
	<path>D:\Jabil\inverter\gen_data\3-146.jpg</path>
	<source>
		<database>Unknown</database>
	</source>
	<size>
		<width>400</width>
		<height>300</height>
		<depth>3</depth>
	</size>
	<segmented>0</segmented>
	<object>
		<name>nut_b</name>
		<pose>Unspecified</pose>
		<truncated>0</truncated>
		<difficult>0</difficult>
		<bndbox>
			<xmin>89</xmin>
			<ymin>78</ymin>
			<xmax>165</xmax>
			<ymax>159</ymax>
		</bndbox>
	</object>
	<object>
		<name>screw_m</name>
		<pose>Unspecified</pose>
		<truncated>0</truncated>
		<difficult>0</difficult>
		<bndbox>
			<xmin>247</xmin>
			<ymin>103</ymin>
			<xmax>291</xmax>
			<ymax>143</ymax>
		</bndbox>
	</object>
</annotation>
