<annotation>
	<folder>2022-06-23_powernut</folder>
	<filename>part5-225548200693.jpg</filename>
	<path>D:\Jabil\inverter\yolov4-keras-bubbliiiing-master\2022-06-23_powernut\part5-225548200693.jpg</path>
	<source>
		<database>Unknown</database>
	</source>
	<size>
		<width>300</width>
		<height>350</height>
		<depth>3</depth>
	</size>
	<segmented>0</segmented>
	<object>
		<name>nut_b</name>
		<pose>Unspecified</pose>
		<truncated>0</truncated>
		<difficult>0</difficult>
		<bndbox>
			<xmin>140</xmin>
			<ymin>136</ymin>
			<xmax>221</xmax>
			<ymax>223</ymax>
		</bndbox>
	</object>
	<object>
		<name>screw_s</name>
		<pose>Unspecified</pose>
		<truncated>0</truncated>
		<difficult>0</difficult>
		<bndbox>
			<xmin>50</xmin>
			<ymin>105</ymin>
			<xmax>89</xmax>
			<ymax>150</ymax>
		</bndbox>
	</object>
	<object>
		<name>screw_s</name>
		<pose>Unspecified</pose>
		<truncated>0</truncated>
		<difficult>0</difficult>
		<bndbox>
			<xmin>81</xmin>
			<ymin>181</ymin>
			<xmax>127</xmax>
			<ymax>218</ymax>
		</bndbox>
	</object>
	<object>
		<name>screw_s</name>
		<pose>Unspecified</pose>
		<truncated>0</truncated>
		<difficult>0</difficult>
		<bndbox>
			<xmin>135</xmin>
			<ymin>238</ymin>
			<xmax>176</xmax>
			<ymax>281</ymax>
		</bndbox>
	</object>
</annotation>
