<annotation>
	<folder>Annotations</folder>
	<filename>part5-213014305270.jpg</filename>
	<path>D:\Jabil\inverter\yolov4-keras-bubbliiiing-master\VOCdevkit\VOC2007\Annotations\part5-213014305270.jpg</path>
	<source>
		<database>Unknown</database>
	</source>
	<size>
		<width>300</width>
		<height>350</height>
		<depth>3</depth>
	</size>
	<segmented>0</segmented>
	<object>
		<name>nut_b</name>
		<pose>Unspecified</pose>
		<truncated>0</truncated>
		<difficult>0</difficult>
		<bndbox>
			<xmin>133</xmin>
			<ymin>126</ymin>
			<xmax>220</xmax>
			<ymax>216</ymax>
		</bndbox>
	</object>
	<object>
		<name>screw_s</name>
		<pose>Unspecified</pose>
		<truncated>0</truncated>
		<difficult>0</difficult>
		<bndbox>
			<xmin>42</xmin>
			<ymin>95</ymin>
			<xmax>85</xmax>
			<ymax>136</ymax>
		</bndbox>
	</object>
	<object>
		<name>screw_s</name>
		<pose>Unspecified</pose>
		<truncated>0</truncated>
		<difficult>0</difficult>
		<bndbox>
			<xmin>77</xmin>
			<ymin>172</ymin>
			<xmax>117</xmax>
			<ymax>211</ymax>
		</bndbox>
	</object>
	<object>
		<name>screw_s</name>
		<pose>Unspecified</pose>
		<truncated>0</truncated>
		<difficult>0</difficult>
		<bndbox>
			<xmin>127</xmin>
			<ymin>231</ymin>
			<xmax>179</xmax>
			<ymax>267</ymax>
		</bndbox>
	</object>
</annotation>
